{
  "relationships": {
    "denominator": "us/census/acs/B07010PR001", 
    "parent": "us/census/acs/B07010PR025"
  }, 
  "name": "$1 to $9,999 or loss and Moved within same municipio and With income in Population 15 Years and Over in Puerto Rico", 
  "extra": {
    "table": "Geographical Mobility in the Past Year by Individual Income in the Past 12 Months (In 2010 Inflation-adjusted Dollars) for Current Residence in Puerto Rico", 
    "universe": "Population 15 Years and Over in Puerto Rico", 
    "ancestors": [
      "Moved within same municipio:", 
      "With income:"
    ], 
    "title": "$1 to $9,999 or loss"
  }
}