{
  "relationships": {
    "denominator": "us/census/acs/B08513001", 
    "parent": "us/census/acs/B08513011"
  }, 
  "name": "Speak English less than \"very well\" within Car, truck, or van - drove alone within Speak Spanish in Workers 16 Years and Over", 
  "extra": {
    "table": "Means of Transportation to Work by Language Spoken at Home and Ability to Speak English for Workplace Geography", 
    "universe": "Workers 16 Years and Over", 
    "ancestors": [
      "Car, truck, or van - drove alone:", 
      "Speak Spanish:"
    ], 
    "title": "Speak English less than \"very well\""
  }
}