{
  "relationships": {
    "denominator": "us/census/acs/B18131001", 
    "parent": "us/census/acs/B18131069"
  }, 
  "name": "Under .50: and 18 years and over in Civilian Noninstitutionalized Population for Whom Poverty Status Is Determined", 
  "extra": {
    "table": "Age by Ratio of Income to Poverty Level in the Past 12 Months by Disability Status and Type", 
    "universe": "Civilian Noninstitutionalized Population for Whom Poverty Status Is Determined", 
    "ancestors": [
      "18 years and over:"
    ], 
    "title": "Under .50:"
  }
}