{
  "relationships": {
    "denominator": "us/census/acs/B23007001", 
    "parent": "us/census/acs/B23007035"
  }, 
  "name": "Unemployed and No children under 18 years and Married-couple family and Husband in labor force and Employed or in Armed Forces and Wife in labor force in Families", 
  "extra": {
    "table": "Presence of Own Children Under 18 Years by Family Type by Employment Status", 
    "universe": "Families", 
    "ancestors": [
      "No children under 18 years:", 
      "Married-couple family:", 
      "Husband in labor force:", 
      "Employed or in Armed Forces:", 
      "Wife in labor force:"
    ], 
    "title": "Unemployed"
  }
}