{
  "relationships": {
    "denominator": "us/census/acs/B23009001", 
    "parent": "us/census/acs/B23009030"
  }, 
  "name": "Other and No children under 18 years and Married-couple family and 3 or more workers in Families", 
  "extra": {
    "table": "Presence of Own Children Under 18 Years by Family Type by Number of Workers in Family in the Past 12 Months", 
    "universe": "Families", 
    "ancestors": [
      "No children under 18 years:", 
      "Married-couple family:", 
      "3 or more workers:"
    ], 
    "title": "Other"
  }
}