{
  "relationships": {
    "denominator": "us/census/acs/B23002A001", 
    "parent": "us/census/acs/B23002A049"
  }, 
  "name": "In labor force: and Female and 20 to 24 years in White Alone Population 16 Years and Over", 
  "extra": {
    "table": "Sex by Age by Employment Status for the Population 16 Years and Over (White Alone)", 
    "universe": "White Alone Population 16 Years and Over", 
    "ancestors": [
      "Female:", 
      "20 to 24 years:"
    ], 
    "title": "In labor force:"
  }
}