{
  "relationships": {
    "denominator": "us/census/acs/B24070001", 
    "parent": "us/census/acs/B24070001"
  }, 
  "name": "Finance and insurance, and real estate and rental and leasing: in Civilian Employed Population 16 Years and Over", 
  "extra": {
    "table": "Industry by Class of Worker for the Civilian Employed Population 16 Years and Over", 
    "universe": "Civilian Employed Population 16 Years and Over", 
    "title": "Finance and insurance, and real estate and rental and leasing:"
  }
}