{
  "relationships": {
    "denominator": "us/census/acs/B24070001", 
    "parent": "us/census/acs/B24070090"
  }, 
  "name": "Transportation and warehousing and Private not-for-profit wage and salary workers and Transportation and warehousing, and utilities in Civilian Employed Population 16 Years and Over", 
  "extra": {
    "table": "Industry by Class of Worker for the Civilian Employed Population 16 Years and Over", 
    "universe": "Civilian Employed Population 16 Years and Over", 
    "ancestors": [
      "Private not-for-profit wage and salary workers:", 
      "Transportation and warehousing, and utilities:"
    ], 
    "title": "Transportation and warehousing"
  }
}